pyget/__init__.py
pyget-0.1.0.dist-info/WHEEL
pyget-0.1.0.dist-info/METADATA
pyget-0.1.0.dist-info/RECORD
